{"stats":{"minecraft:killed":{"minecraft:horse":1,"minecraft:parrot":1},"minecraft:custom":{"minecraft:time_since_rest":149770,"minecraft:walk_one_cm":231235,"minecraft:interact_with_furnace":3,"minecraft:sprint_one_cm":123898,"minecraft:damage_taken":220,"minecraft:mob_kills":5,"minecraft:drop":68,"minecraft:inspect_hopper":1,"minecraft:damage_dealt":782,"minecraft:tune_noteblock":18,"minecraft:fly_one_cm":731729,"minecraft:crouch_one_cm":8729,"minecraft:play_one_minute":150359,"minecraft:deaths":1,"minecraft:sneak_time":4357,"minecraft:aviate_one_cm":11891,"minecraft:jump":294,"minecraft:leave_game":1,"minecraft:walk_on_water_one_cm":1486,"minecraft:time_since_death":149732,"minecraft:inspect_dispenser":1,"minecraft:horse_one_cm":263090},"minecraft:dropped":{"minecraft:zombie_villager_spawn_egg":1,"minecraft:sugar_cane":1,"minecraft:bone_meal":1,"minecraft:phantom_spawn_egg":1,"minecraft:glowstone_dust":2,"minecraft:paper":61,"minecraft:skeleton_horse_spawn_egg":1},"minecraft:used":{"minecraft:redstone_torch":5,"minecraft:water_bucket":1,"minecraft:flower_pot":3,"minecraft:jack_o_lantern":14,"minecraft:cyan_terracotta":3,"minecraft:snow_block":2,"minecraft:polished_andesite":2,"minecraft:zombie_villager_spawn_egg":6,"minecraft:sign":3,"minecraft:cauldron":1,"minecraft:horse_spawn_egg":8,"minecraft:bedrock":1,"minecraft:diamond_sword":16,"minecraft:anvil":2,"minecraft:bow":9,"minecraft:hopper":3,"minecraft:phantom_spawn_egg":9,"minecraft:white_concrete":3,"minecraft:shulker_spawn_egg":1,"minecraft:skeleton_horse_spawn_egg":1,"minecraft:snowball":22},"minecraft:picked_up":{"minecraft:paper":1,"minecraft:pufferfish":1,"minecraft:tropical_fish":8,"minecraft:bone_meal":2,"minecraft:glowstone_dust":1}},"DataVersion":1631}